<?xml version="1.0" encoding="UTF-8" ?>
<!DOCTYPE Entity SYSTEM "jbo_03_01.dtd">
<!---->
<Entity
  xmlns="http://xmlns.oracle.com/bc4j"
  Name="Currency"
  Version="12.1.2.66.68"
  InheritPersonalization="merge"
  DBObjectType="table"
  DBObjectName="CURRENCY"
  AliasName="Currency"
  BindingStyle="OracleName"
  RowClass="ua.divas.model.CurrencyImpl">
  <DesignTime>
    <Attr Name="_codeGenFlag2" Value="Access"/>
    <Attr Name="_isCodegen" Value="true"/>
  </DesignTime>
  <Attribute
    Name="Id"
    IsNotNull="true"
    Precision="50"
    ColumnName="ID"
    SQLType="VARCHAR"
    Type="java.lang.String"
    ColumnType="VARCHAR2"
    TableName="CURRENCY"
    PrimaryKey="true">
    <DesignTime>
      <Attr Name="_DisplaySize" Value="50"/>
    </DesignTime>
    <Properties>
      <SchemaBasedProperties>
        <LABEL
          ResId="ua.divas.model.Currency.Id_LABEL"/>
        <TOOLTIP
          ResId="ua.divas.model.Currency.Id_TOOLTIP"/>
      </SchemaBasedProperties>
    </Properties>
  </Attribute>
  <Attribute
    Name="IsGroup"
    Precision="1"
    Scale="0"
    ColumnName="IS_GROUP"
    SQLType="NUMERIC"
    Type="java.lang.Integer"
    ColumnType="NUMBER"
    TableName="CURRENCY"
    DefaultValue="0">
    <Properties>
      <SchemaBasedProperties>
        <LABEL
          ResId="ua.divas.model.Currency.IsGroup_LABEL"/>
        <TOOLTIP
          ResId="ua.divas.model.Currency.IsGroup_TOOLTIP"/>
      </SchemaBasedProperties>
    </Properties>
  </Attribute>
  <Attribute
    Name="ParentId"
    Precision="50"
    ColumnName="PARENT_ID"
    SQLType="VARCHAR"
    Type="java.lang.String"
    ColumnType="VARCHAR2"
    TableName="CURRENCY">
    <DesignTime>
      <Attr Name="_DisplaySize" Value="50"/>
    </DesignTime>
    <Properties>
      <SchemaBasedProperties>
        <LABEL
          ResId="ua.divas.model.Currency.ParentId_LABEL"/>
        <TOOLTIP
          ResId="ua.divas.model.Currency.ParentId_TOOLTIP"/>
      </SchemaBasedProperties>
    </Properties>
  </Attribute>
  <Attribute
    Name="Deleted"
    IsNotNull="true"
    Precision="1"
    Scale="0"
    ColumnName="DELETED"
    SQLType="NUMERIC"
    Type="java.lang.Integer"
    ColumnType="NUMBER"
    TableName="CURRENCY"
    DefaultValue="0">
    <Properties>
      <SchemaBasedProperties>
        <LABEL
          ResId="ua.divas.model.Currency.Deleted_LABEL"/>
        <TOOLTIP
          ResId="ua.divas.model.Currency.Deleted_TOOLTIP"/>
      </SchemaBasedProperties>
    </Properties>
  </Attribute>
  <Attribute
    Name="Fullname"
    IsNotNull="true"
    Precision="5"
    ColumnName="FULLNAME"
    SQLType="VARCHAR"
    Type="java.lang.String"
    ColumnType="VARCHAR2"
    TableName="CURRENCY">
    <DesignTime>
      <Attr Name="_DisplaySize" Value="5"/>
    </DesignTime>
    <Properties>
      <SchemaBasedProperties>
        <LABEL
          ResId="ua.divas.model.Currency.Fullname_LABEL"/>
        <TOOLTIP
          ResId="ua.divas.model.Currency.Fullname_TOOLTIP"/>
      </SchemaBasedProperties>
    </Properties>
  </Attribute>
  <Attribute
    Name="Code"
    Precision="3"
    ColumnName="CODE"
    SQLType="VARCHAR"
    Type="java.lang.String"
    ColumnType="VARCHAR2"
    TableName="CURRENCY">
    <DesignTime>
      <Attr Name="_DisplaySize" Value="3"/>
    </DesignTime>
    <Properties>
      <SchemaBasedProperties>
        <LABEL
          ResId="ua.divas.model.Currency.Code_LABEL"/>
        <TOOLTIP
          ResId="ua.divas.model.Currency.Code_TOOLTIP"/>
      </SchemaBasedProperties>
    </Properties>
  </Attribute>
  <Attribute
    Name="Namefull"
    Precision="50"
    ColumnName="NAMEFULL"
    SQLType="VARCHAR"
    Type="java.lang.String"
    ColumnType="VARCHAR2"
    TableName="CURRENCY">
    <DesignTime>
      <Attr Name="_DisplaySize" Value="50"/>
    </DesignTime>
    <Properties>
      <SchemaBasedProperties>
        <LABEL
          ResId="ua.divas.model.Currency.Namefull_LABEL"/>
        <TOOLTIP
          ResId="ua.divas.model.Currency.Namefull_TOOLTIP"/>
      </SchemaBasedProperties>
    </Properties>
  </Attribute>
  <Attribute
    Name="Version"
    ColumnName="VERSION"
    SQLType="TIMESTAMP"
    Type="java.sql.Timestamp"
    ColumnType="TIMESTAMP"
    TableName="CURRENCY">
    <Properties>
      <SchemaBasedProperties>
        <LABEL
          ResId="ua.divas.model.Currency.Version_LABEL"/>
        <TOOLTIP
          ResId="ua.divas.model.Currency.Version_TOOLTIP"/>
      </SchemaBasedProperties>
    </Properties>
  </Attribute>
  <Attribute
    Name="Predefined"
    IsNotNull="true"
    Precision="1"
    Scale="0"
    ColumnName="PREDEFINED"
    SQLType="NUMERIC"
    Type="java.lang.Integer"
    ColumnType="NUMBER"
    TableName="CURRENCY"
    DefaultValue="0">
    <Properties>
      <SchemaBasedProperties>
        <LABEL
          ResId="ua.divas.model.Currency.Predefined_LABEL"/>
        <TOOLTIP
          ResId="ua.divas.model.Currency.Predefined_TOOLTIP"/>
      </SchemaBasedProperties>
    </Properties>
  </Attribute>
  <Attribute
    Name="IdXml"
    IsNotNull="true"
    Precision="3"
    ColumnName="ID_XML"
    SQLType="VARCHAR"
    Type="java.lang.String"
    ColumnType="VARCHAR2"
    TableName="CURRENCY"
    DefaultValue="0">
    <DesignTime>
      <Attr Name="_DisplaySize" Value="3"/>
    </DesignTime>
    <Permission
      target="ua.divas.model.Currency.IdXml"
      permissionClass="oracle.adf.share.security.authorization.EntityAttributePermission">
      <privilege-map
        operation="update"
        privilege="update"/>
    </Permission>
    <Properties>
      <SchemaBasedProperties>
        <LABEL
          ResId="ua.divas.model.Currency.IdXml_LABEL"/>
        <TOOLTIP
          ResId="ua.divas.model.Currency.IdXml_TOOLTIP"/>
      </SchemaBasedProperties>
    </Properties>
  </Attribute>
  <AccessorAttribute
    Name="ExRatesSettings"
    Association="ua.divas.model.ExRatesSettingsCurrencFk1Assoc"
    AssociationEnd="ua.divas.model.ExRatesSettingsCurrencFk1Assoc.ExRatesSettings"
    AssociationOtherEnd="ua.divas.model.ExRatesSettingsCurrencFk1Assoc.Currency"
    Type="oracle.jbo.server.EntityImpl"
    IsUpdateable="true"/>
  <AccessorAttribute
    Name="Kassa"
    Association="ua.divas.model.KassaCurrencyFk1Assoc"
    AssociationEnd="ua.divas.model.KassaCurrencyFk1Assoc.Kassa"
    AssociationOtherEnd="ua.divas.model.KassaCurrencyFk1Assoc.Currency"
    Type="oracle.jbo.RowIterator"
    IsUpdateable="false"/>
  <AccessorAttribute
    Name="Moves"
    Association="ua.divas.model.MovesCurrencyFk1Assoc"
    AssociationEnd="ua.divas.model.MovesCurrencyFk1Assoc.Moves"
    AssociationOtherEnd="ua.divas.model.MovesCurrencyFk1Assoc.Currency"
    Type="oracle.jbo.RowIterator"
    IsUpdateable="false"/>
  <AccessorAttribute
    Name="Moves1"
    Association="ua.divas.model.MovesCurrencyFk2Assoc"
    AssociationEnd="ua.divas.model.MovesCurrencyFk2Assoc.Moves1"
    AssociationOtherEnd="ua.divas.model.MovesCurrencyFk2Assoc.Currency1"
    Type="oracle.jbo.RowIterator"
    IsUpdateable="false"/>
  <AccessorAttribute
    Name="Orders"
    Association="ua.divas.model.OrdersCurrencyFk1Assoc"
    AssociationEnd="ua.divas.model.OrdersCurrencyFk1Assoc.Orders"
    AssociationOtherEnd="ua.divas.model.OrdersCurrencyFk1Assoc.Currency"
    Type="oracle.jbo.RowIterator"
    IsUpdateable="false"/>
  <AccessorAttribute
    Name="RegRates"
    Association="ua.divas.model.RegRatesFk1Assoc"
    AssociationEnd="ua.divas.model.RegRatesFk1Assoc.RegRates"
    AssociationOtherEnd="ua.divas.model.RegRatesFk1Assoc.Currency"
    Type="oracle.jbo.RowIterator"
    IsUpdateable="false"/>
  <AccessorAttribute
    Name="UserSettings"
    Association="ua.divas.model.UserSettingsCurrencyFk1Assoc"
    AssociationEnd="ua.divas.model.UserSettingsCurrencyFk1Assoc.UserSettings"
    AssociationOtherEnd="ua.divas.model.UserSettingsCurrencyFk1Assoc.Currency"
    Type="oracle.jbo.RowIterator"
    IsUpdateable="false"/>
  <AccessorAttribute
    Name="OtherZatraty"
    Association="ua.divas.model.OtherZatratyFk3Assoc"
    AssociationEnd="ua.divas.model.OtherZatratyFk3Assoc.OtherZatraty"
    AssociationOtherEnd="ua.divas.model.OtherZatratyFk3Assoc.Currency"
    Type="oracle.jbo.RowIterator"
    IsUpdateable="false"/>
  <AccessorAttribute
    Name="StartOst"
    Association="ua.divas.model.StartOstFk3Assoc"
    AssociationEnd="ua.divas.model.StartOstFk3Assoc.StartOst"
    AssociationOtherEnd="ua.divas.model.StartOstFk3Assoc.Currency"
    Type="oracle.jbo.RowIterator"
    IsUpdateable="false"/>
  <AccessorAttribute
    Name="ProfitDistrib"
    Association="ua.divas.model.ProfitDistribFk3Assoc"
    AssociationEnd="ua.divas.model.ProfitDistribFk3Assoc.ProfitDistrib"
    AssociationOtherEnd="ua.divas.model.ProfitDistribFk3Assoc.Currency"
    Type="oracle.jbo.RowIterator"
    IsUpdateable="false"/>
  <Key
    Name="CurrencyChk1">
    <DesignTime>
      <Attr Name="_DBObjectName" Value="CURRENCY_CHK1"/>
      <Attr Name="_checkCondition" Value="deleted in (0,1)"/>
      <Attr Name="_isCheck" Value="true"/>
    </DesignTime>
    <AttrArray Name="Attributes"/>
  </Key>
  <Key
    Name="CurrencyChk2">
    <DesignTime>
      <Attr Name="_DBObjectName" Value="CURRENCY_CHK2"/>
      <Attr Name="_checkCondition" Value="PREDEFINED in (0,1)"/>
      <Attr Name="_isCheck" Value="true"/>
    </DesignTime>
    <AttrArray Name="Attributes"/>
  </Key>
  <Key
    Name="CurrencyPk"
    PrimaryKey="true">
    <DesignTime>
      <Attr Name="_DBObjectName" Value="CURRENCY_PK"/>
    </DesignTime>
    <AttrArray Name="Attributes">
      <Item Value="ua.divas.model.Currency.Id"/>
    </AttrArray>
  </Key>
  <ResourceBundle>
    <PropertiesBundle
      PropertiesFile="ua.divas.model.ModelBundle"/>
  </ResourceBundle>
</Entity>
